pdf_generator/__main__.py
pdf_generator/convert.py
oneandtwoexample-0.2.1.dist-info/METADATA
oneandtwoexample-0.2.1.dist-info/WHEEL
oneandtwoexample-0.2.1.dist-info/top_level.txt
oneandtwoexample-0.2.1.dist-info/RECORD
